taxonomy-0.10.2.dist-info/METADATA
taxonomy-0.10.2.dist-info/WHEEL
taxonomy-0.10.2.dist-info/license_files/LICENSE
taxonomy/__init__.py
taxonomy/__init__.pyi
taxonomy/py.typed
taxonomy/taxonomy.cpython-314-darwin.so
taxonomy-0.10.2.dist-info/RECORD
