Metadata-Version: 2.1
Name: taxonomy
Version: 0.10.2
License-File: LICENSE
Summary: Routines for loading, saving, and manipulating taxonomic trees
Keywords: taxonomy,bioinformatics
Author: Vincent Prouillet <vincent@onecodex.com>
Author-email: Vincent Prouillet <vincent@onecodex.com>
License: MIT
Project-URL: Source Code, https://github.com/onecodex/taxonomy
